mattebox/__init__.py
mattebox/app.py
mattebox/auth.py
mattebox/consts.py
mattebox/exceptions.py
mattebox/helpers.py
mattebox/types.py
mattebox-0.1.1.dist-info/LICENSE
mattebox-0.1.1.dist-info/WHEEL
mattebox-0.1.1.dist-info/METADATA
mattebox-0.1.1.dist-info/RECORD
