Metadata-Version: 2.1
Name: mattebox
Version: 0.1.1
Summary: Unofficial library for MatteBOX API.
License: ISC
Author: samedamci
Author-email: samedamci@disroot.org
Requires-Python: >=3.9.2,<4.0.0
Classifier: License :: OSI Approved
Classifier: Programming Language :: Python :: 3
Requires-Dist: m3u8 (>=0.9.0,<0.10.0)
Requires-Dist: requests (>=2.26.0,<3.0.0)
